[
  {
    "id": "41",
    "input": "\"축구\", \"펜싱\", \"배구\", \"하이킹\", \"민달팽이\" 단어가 모두\"운동\"유형입니까? \"예\" 또는 \"아니오\" 중 하나로 답하십시오.\""
  },
  {
    "id": "88",
    "input": "\"모임\", \"마을\", \"등급\", \"구\", \"조언\" 단어가 모두\"사회\"유형입니까? \"예\" 또는 \"아니오\" 중 하나로 답하십시오.\""
  },
  {
    "id": "105",
    "input": "\"벨라\", \"귀\", \"파도타기\", \"하키\", \"골프\" 단어가 모두\"운동\"유형입니까? \"예\" 또는 \"아니오\" 중 하나로 답하십시오.\""
  },
  {
    "id": "161",
    "input": "\"풀\", \"자매\", \"삼촌\", \"형제\", \"조카\" 단어가 모두\"가족\"유형입니까? \"예\" 또는 \"아니오\" 중 하나로 답하십시오.\""
  },
  {
    "id": "366",
    "input": "\"증손녀\", \"수요\", \"생산\", \"경제\", \"무역\" 단어가 모두\"경제\"유형입니까? \"예\" 또는 \"아니오\" 중 하나로 답하십시오.\""
  },
  {
    "id": "562",
    "input": "\"그림\", \"자전거\", \"도로\", \"정류소\", \"운송\" 단어가 모두\"운송\"유형입니까? \"예\" 또는 \"아니오\" 중 하나로 답하십시오.\""
  },
  {
    "id": "579",
    "input": "\"산림\", \"해양\", \"해변\", \"산\", \"택시\" 단어가 모두\"지리\"유형입니까? \"예\" 또는 \"아니오\" 중 하나로 답하십시오.\""
  },
  {
    "id": "596",
    "input": "\"피망\", \"속도\", \"배경\", \"넓은\", \"가속\" 단어가 모두\"공간과 양\"유형입니까? \"예\" 또는 \"아니오\" 중 하나로 답하십시오.\""
  },
  {
    "id": "890",
    "input": "\"거주지\", \"의무\", \"카마\", \"집\", \"침실\" 단어가 모두\"가정\"유형입니까? \"예\" 또는 \"아니오\" 중 하나로 답하십시오.\""
  },
  {
    "id": "940",
    "input": "\"입구\", \"가정\", \"거주지\", \"은행\", \"창\" 단어가 모두\"가정\"유형입니까? \"예\" 또는 \"아니오\" 중 하나로 답하십시오.\""
  },
  {
    "id": "967",
    "input": "\"성인\", \"성격\", \"하나\", \"인류\", \"동물\" 단어가 모두\"사람\"유형입니까? \"예\" 또는 \"아니오\" 중 하나로 답하십시오.\""
  },
  {
    "id": "1022",
    "input": "\"아저씨\", \"배경\", \"사람\", \"인류\", \"늙은\" 단어가 모두\"사람\" 나타냅니까? \"예\" 또는 \"아니오\" 중 하나로 답하십시오."
  },
  {
    "id": "1153",
    "input": "\"인간\", \"총량\", \"페소\", \"센티미터\", \"그램\" 단어가 모두\"측정\" 나타냅니까? \"예\" 또는 \"아니오\" 중 하나로 답하십시오."
  },
  {
    "id": "1319",
    "input": "\"거래\", \"경제\", \"휴식\", \"돈\", \"무역\" 단어가 모두\"경제\" 나타냅니까? \"예\" 또는 \"아니오\" 중 하나로 답하십시오."
  },
  {
    "id": "1450",
    "input": "\"시리즈\", \"확률\", \"동의\", \"배구\", \"실패\" 단어가 모두\"추상명사\" 나타냅니까? \"예\" 또는 \"아니오\" 중 하나로 답하십시오."
  },
  {
    "id": "1501",
    "input": "\"총량\", \"밀리리터\", \"센티미터\", \"고통\", \"그램\" 단어가 모두\"측정\" 나타냅니까? \"예\" 또는 \"아니오\" 중 하나로 답하십시오."
  },
  {
    "id": "1783",
    "input": "\"가위\", \"클립\", \"지우개\", \"이유\", \"형광펜\" 단어가 모두\"문구류\" 나타냅니까? \"예\" 또는 \"아니오\" 중 하나로 답하십시오."
  },
  {
    "id": "1796",
    "input": "\"공포\", \"음악\", \"드라마\", \"긴장감\", \"산사태\" 단어가 모두\"영화장르\" 나타냅니까? \"예\" 또는 \"아니오\" 중 하나로 답하십시오."
  },
  {
    "id": "1902",
    "input": "\"체스\", \"낚시\", \"자수\", \"핸드볼\", \"명상\" 단어가 모두\"취미\" 나타냅니까? \"예\" 또는 \"아니오\" 중 하나로 답하십시오."
  },
  {
    "id": "2005",
    "input": "다음 목록 [\"사슴\", \"화재\", \"지진\", \"산사태\", \"태풍\"]에\"자연재해\" 포함되어 있습니까? \"예\" 또는 \"아니오\" 중 하나로 답하십시오."
  },
  {
    "id": "2047",
    "input": "다음 목록 [\"바\u001f\", \"보석점\", \"엉덩이\", \"은행\", \"약초상점\"]에\"직장\" 포함되어 있습니까? \"예\" 또는 \"아니오\" 중 하나로 답하십시오."
  },
  {
    "id": "2048",
    "input": "다음 목록 [\"생명체\", \"태어남\", \"삶\", \"죽음\", \"가족\"]에\"생명\" 포함되어 있습니까? \"예\" 또는 \"아니오\" 중 하나로 답하십시오."
  },
  {
    "id": "2135",
    "input": "다음 목록 [\"금요일\", \"법\", \"일요일\", \"월요일\", \"화요일\"]에\"요일\" 포함되어 있습니까? \"예\" 또는 \"아니오\" 중 하나로 답하십시오."
  },
  {
    "id": "2170",
    "input": "다음 목록 [\"물고기\", \"무역\", \"요금\", \"수요\", \"용기\"]에\"경제\" 포함되어 있습니까? \"예\" 또는 \"아니오\" 중 하나로 답하십시오."
  },
  {
    "id": "2238",
    "input": "다음 목록 [\"공포\", \"장관\", \"상상\", \"드라마\", \"긴장감\"]에\"영화장르\" 포함되어 있습니까? \"예\" 또는 \"아니오\" 중 하나로 답하십시오."
  },
  {
    "id": "2605",
    "input": "다음 목록 [\"요리\", \"사진\", \"글쓰기\", \"의자\", \"게임\"]에\"취미\" 포함되어 있습니까? \"예\" 또는 \"아니오\" 중 하나로 답하십시오."
  },
  {
    "id": "2650",
    "input": "다음 목록 [\"도서관\", \"화원\", \"약국\", \"금속\", \"사무실\"]에\"직장\" 포함되어 있습니까? \"예\" 또는 \"아니오\" 중 하나로 답하십시오."
  },
  {
    "id": "2678",
    "input": "다음 목록 [\"의미하다\", \"귀\", \"달\", \"판매자\", \"노래\"]에\"행위동사\" 포함되어 있습니까? \"예\" 또는 \"아니오\" 중 하나로 답하십시오."
  },
  {
    "id": "2732",
    "input": "다음 목록 [\"주제\", \"과정\", \"4월\", \"방어\", \"성취\"]에\"추상명사\" 포함되어 있습니까? \"예\" 또는 \"아니오\" 중 하나로 답하십시오."
  },
  {
    "id": "2827",
    "input": "다음 목록 [\"선물\", \"삶\", \"태어남\", \"종류\", \"복제\"]에\"생명\" 포함되어 있습니까? \"예\" 또는 \"아니오\" 중 하나로 답하십시오."
  }
]