[
  {
    "id": "22",
    "input": "Delle parole \"così\", \"basso\", \"peggio\", \"presenza\" e \"freddamente\", qual è la parola più comunemente associata con \"sostantivi astratti\"?"
  },
  {
    "id": "41",
    "input": "Delle parole \"vendere\", \"comunicare\", \"potere\", \"accettare\" e \"sabato\", qual è la parola più comunemente associata con \"giorni della settimana\"?"
  },
  {
    "id": "46",
    "input": "Delle parole \"surf\", \"aromatico\", \"fresco\", \"flessibile\" e \"delicato\", qual è la parola più comunemente associata con \"sport\"?"
  },
  {
    "id": "88",
    "input": "Delle parole \"fava\", \"farmacia\", \"ospedale\", \"banca\" e \"hotel\", qual è la parola più comunemente associata con \"verdure\"?"
  },
  {
    "id": "105",
    "input": "Delle parole \"neonato\", \"gente\", \"economia\", \"bambina\" e \"uomo\", qual è la parola più comunemente associata con \"termini economici\"?"
  },
  {
    "id": "161",
    "input": "Delle parole \"due\", \"minoranza\", \"luogo\", \"decremento\" e \"ampiezza\", qual è la parola più comunemente associata con \"numeri\"?"
  },
  {
    "id": "201",
    "input": "Delle parole \"di\", \"per\", \"da\", \"tragedia\" e \"mediante\", qual è la parola più comunemente associata con \"genere di film\"?"
  },
  {
    "id": "244",
    "input": "Delle parole \"scale\", \"edificio\", \"annoiarsi\", \"stanza\" e \"camera\", qual è la parola più comunemente associata con \"verbi di emozione\"?"
  },
  {
    "id": "252",
    "input": "Delle parole \"magenta\", \"fallimento\", \"senso\", \"fatica\" e \"forza\", qual è la parola più comunemente associata con \"colori\"?"
  },
  {
    "id": "288",
    "input": "Delle parole \"chitarra\", \"mercoledì\", \"venerdì\", \"domenica\" e \"giovedì\", qual è la parola più comunemente associata con \"strumenti musicali\"?"
  },
  {
    "id": "366",
    "input": "Delle parole \"niente\", \"altrettanto\", \"abbastanza\", \"assai\" e \"millilitro\", qual è la parola più comunemente associata con \"misure\"?"
  },
  {
    "id": "367",
    "input": "Delle parole \"bronzo\", \"fuoco\", \"ferro\", \"aria\" e \"cervello\", qual è la parola più comunemente associata con \"parti del corpo umano\"?"
  },
  {
    "id": "385",
    "input": "Delle parole \"cassiere\", \"amministratore\", \"dentista\", \"esistere\" e \"falegname\", qual è la parola più comunemente associata con \"verbi di esistenza\"?"
  },
  {
    "id": "431",
    "input": "Delle parole \"dieci\", \"otto\", \"come\", \"sei\" e \"tre\", qual è la parola più comunemente associata con \"congiunzioni\"?"
  },
  {
    "id": "535",
    "input": "Delle parole \"conseguire\", \"distribuire\", \"abbandonare\", \"verde\" e \"controllare\", qual è la parola più comunemente associata con \"colori\"?"
  },
  {
    "id": "538",
    "input": "Delle parole \"naso\", \"cuore\", \"pelo\", \"tallone\" e \"guanti\", qual è la parola più comunemente associata con \"vestiti\"?"
  },
  {
    "id": "541",
    "input": "Delle parole \"alquanto\", \"rallegrarsi\", \"tanto\", \"tutto\" e \"soltanto\", qual è la parola più comunemente associata con \"verbi di emozione\"?"
  },
  {
    "id": "562",
    "input": "Delle parole \"pantoloni\", \"stivali\", \"manica\", \"occhiali\" e \"intorno\", qual è la parola più comunemente associata con \"avverbi di luogo\"?"
  },
  {
    "id": "579",
    "input": "Delle parole \"batteria\", \"pianoforte\", \"violino\", \"violoncello\" e \"specie\", qual è la parola più comunemente associata con \"aspetti della vita\"?"
  },
  {
    "id": "594",
    "input": "Delle parole \"traffico\", \"signora\", \"umanità\", \"neonato\" e \"gente\", qual è la parola più comunemente associata con \"trasporto\"?"
  },
  {
    "id": "596",
    "input": "Delle parole \"soltanto\", \"morte\", \"più\", \"altrettanto\" e \"parecchio\", qual è la parola più comunemente associata con \"aspetti della vita\"?"
  },
  {
    "id": "610",
    "input": "Delle parole \"giovedì\", \"venerdì\", \"domenica\", \"martedì\" e \"beneficio\", qual è la parola più comunemente associata con \"sostantivi astratti\"?"
  },
  {
    "id": "650",
    "input": "Delle parole \"tardi\", \"crescere\", \"comunque\", \"mentre\" e \"ancora\", qual è la parola più comunemente associata con \"verbi di esistenza\"?"
  },
  {
    "id": "691",
    "input": "Delle parole \"chilo\", \"terremoto\", \"chilometro\", \"quantità\" e \"peso\", qual è la parola più comunemente associata con \"catastrofe naturale\"?"
  },
  {
    "id": "709",
    "input": "Delle parole \"settembre\", \"due\", \"febbraio\", \"dicembre\" e \"aprile\", qual è la parola più comunemente associata con \"numeri\"?"
  },
  {
    "id": "724",
    "input": "Delle parole \"donna\", \"libreria\", \"banca\", \"supermercato\" e \"scuola\", qual è la parola più comunemente associata con \"persone\"?"
  },
  {
    "id": "763",
    "input": "Delle parole \"media\", \"quantità\", \"agosto\", \"grammo\" e \"peso\", qual è la parola più comunemente associata con \"mesi dell'anno\"?"
  },
  {
    "id": "795",
    "input": "Delle parole \"appiccicare\", \"catturare\", \"venire\", \"scuola\" e \"andare\", qual è la parola più comunemente associata con \"posti di lavoro\"?"
  },
  {
    "id": "827",
    "input": "Delle parole \"deputato\", \"idraulico\", \"giornalista\", \"ciclismo\" e \"macellaio\", qual è la parola più comunemente associata con \"sport\"?"
  },
  {
    "id": "843",
    "input": "Delle parole \"professore\", \"chilometro\", \"millilitro\", \"millimetro\" e \"centimetro\", qual è la parola più comunemente associata con \"professioni\"?"
  },
  {
    "id": "890",
    "input": "Delle parole \"intercontinentale\", \"zucca\", \"barbabietola\", \"spinaci\" e \"melanzana\", qual è la parola più comunemente associata con \"aggettivi qualificativi\"?"
  },
  {
    "id": "940",
    "input": "Delle parole \"intenzionalmente\", \"vite\", \"cavo\", \"telecamera\" e \"martello\", qual è la parola più comunemente associata con \"avverbi qualificativi\"?"
  },
  {
    "id": "958",
    "input": "Delle parole \"vite\", \"chiodo\", \"calcio\", \"ago\" e \"fune\", qual è la parola più comunemente associata con \"sport\"?"
  },
  {
    "id": "967",
    "input": "Delle parole \"donna\", \"gente\", \"bambina\", \"sei\" e \"uomo\", qual è la parola più comunemente associata con \"numeri\"?"
  },
  {
    "id": "979",
    "input": "Delle parole \"veicolo\", \"automobile\", \"aereo\", \"politica\" e \"rotta\", qual è la parola più comunemente associata con \"termini socio-politici\"?"
  },
  {
    "id": "993",
    "input": "Delle parole \"forse\", \"difficilmente\", \"anche\", \"mai\" e \"luglio\", qual è la parola più comunemente associata con \"mesi dell'anno\"?"
  },
  {
    "id": "1022",
    "input": "Qual è la parola più correlata con la categoria \"sostantivi astratti\" tra le parole \"così\", \"basso\", \"peggio\", \"presenza\" e \"freddamente\"?"
  },
  {
    "id": "1048",
    "input": "Qual è la parola più correlata con la categoria \"misure\" tra le parole \"accettare\", \"bere\", \"aspettare\", \"trovare\" e \"millilitro\"?"
  },
  {
    "id": "1053",
    "input": "Qual è la parola più correlata con la categoria \"numeri\" tra le parole \"chiave\", \"cavo\", \"cucchiaino\", \"cinque\" e \"fune\"?"
  },
  {
    "id": "1153",
    "input": "Qual è la parola più correlata con la categoria \"persone\" tra le parole \"morte\", \"gente\", \"specie\", \"nascita\" e \"essere\"?"
  },
  {
    "id": "1205",
    "input": "Qual è la parola più correlata con la categoria \"aggettivi numerali ordinali\" tra le parole \"viale\", \"traffico\", \"ultimo\", \"aereo\" e \"monopattino\"?"
  },
  {
    "id": "1232",
    "input": "Qual è la parola più correlata con la categoria \"sostantivi astratti\" tra le parole \"tema\", \"adolescente\", \"umano\", \"adulto\" e \"infante\"?"
  },
  {
    "id": "1268",
    "input": "Qual è la parola più correlata con la categoria \"arredamento o parti di casa\" tra le parole \"novembre\", \"luglio\", \"ottobre\", \"marzo\" e \"appartamento\"?"
  },
  {
    "id": "1319",
    "input": "Qual è la parola più correlata con la categoria \"professioni\" tra le parole \"nostro\", \"macellaio\", \"vostro\", \"loro\" e \"mio\"?"
  },
  {
    "id": "1384",
    "input": "Qual è la parola più correlata con la categoria \"arredamento o parti di casa\" tra le parole \"impossibile\", \"distinto\", \"manuale\", \"generale\" e \"tavolo\"?"
  },
  {
    "id": "1408",
    "input": "Qual è la parola più correlata con la categoria \"colori\" tra le parole \"terzo\", \"primo\", \"quinto\", \"milionesimo\" e \"magenta\"?"
  },
  {
    "id": "1437",
    "input": "Qual è la parola più correlata con la categoria \"aspetti della vita\" tra le parole \"banca\", \"nascita\", \"supermercato\", \"salumeria\" e \"ristorante\"?"
  },
  {
    "id": "1444",
    "input": "Qual è la parola più correlata con la categoria \"verbi di emozione\" tra le parole \"piombo\", \"fango\", \"infastidirsi\", \"terracotta\" e \"ghiaccio\"?"
  },
  {
    "id": "1450",
    "input": "Qual è la parola più correlata con la categoria \"colori\" tra le parole \"mediante\", \"in\", \"azzurro\", \"tra\" e \"di\"?"
  },
  {
    "id": "1491",
    "input": "Qual è la parola più correlata con la categoria \"aspetti della vita\" tra le parole \"avvicinare\", \"alzare\", \"lanciare\", \"specie\" e \"scalciare\"?"
  },
  {
    "id": "1501",
    "input": "Qual è la parola più correlata con la categoria \"termini socio-politici\" tra le parole \"canottaggio\", \"nuoto\", \"escursionismo\", \"hockey\" e \"regione\"?"
  },
  {
    "id": "1506",
    "input": "Qual è la parola più correlata con la categoria \"sport\" tra le parole \"hockey\", \"andare\", \"catturare\", \"togliere\" e \"tirare\"?"
  },
  {
    "id": "1536",
    "input": "Qual è la parola più correlata con la categoria \"classi grammaticali\" tra le parole \"articolo\", \"fantastico\", \"thriller\", \"romantico\" e \"noir\"?"
  },
  {
    "id": "1587",
    "input": "Qual è la parola più correlata con la categoria \"sport\" tra le parole \"viale\", \"pallamano\", \"stazione\", \"bus\" e \"aeroporto\"?"
  },
  {
    "id": "1677",
    "input": "Qual è la parola più correlata con la categoria \"preprosizioni\" tra le parole \"intercontinentale\", \"da\", \"diverso\", \"solito\" e \"rurale\"?"
  },
  {
    "id": "1728",
    "input": "Qual è la parola più correlata con la categoria \"aggettivi numerali ordinali\" tra le parole \"perché\", \"e\", \"se\", \"centesimo\" e \"benché\"?"
  },
  {
    "id": "1751",
    "input": "Qual è la parola più correlata con la categoria \"professioni\" tra le parole \"ampio\", \"grande\", \"piccolo\", \"stretto\" e \"attrice\"?"
  },
  {
    "id": "1777",
    "input": "Qual è la parola più correlata con la categoria \"classi grammaticali\" tra le parole \"congiunzione\", \"essere\", \"riproduzione\", \"morte\" e \"specie\"?"
  },
  {
    "id": "1783",
    "input": "Qual è la parola più correlata con la categoria \"sport\" tra le parole \"surf\", \"giovedì\", \"domenica\", \"sabato\" e \"venerdì\"?"
  },
  {
    "id": "1793",
    "input": "Qual è la parola più correlata con la categoria \"persone\" tra le parole \"commercio\", \"prodotto\", \"servizio\", \"compagnia\" e \"bambino\"?"
  },
  {
    "id": "1796",
    "input": "Qual è la parola più correlata con la categoria \"verbi di esistenza\" tra le parole \"cavallo\", \"crescere\", \"lucertola\", \"coniglio\" e \"ragno\"?"
  },
  {
    "id": "1819",
    "input": "Qual è la parola più correlata con la categoria \"verbi di movimento\" tra le parole \"consolare\", \"amare\", \"battere\", \"arrabbiarsi\" e \"rallegrarsi\"?"
  },
  {
    "id": "1902",
    "input": "Qual è la parola più correlata con la categoria \"persone\" tra le parole \"sottile\", \"signore\", \"stretto\", \"ampio\" e \"gran\"?"
  },
  {
    "id": "1932",
    "input": "Qual è la parola più correlata con la categoria \"strumenti musicali\" tra le parole \"partito\", \"divieto\", \"riunione\", \"violoncello\" e \"struttura\"?"
  },
  {
    "id": "1971",
    "input": "Qual è la parola più correlata con la categoria \"materiali\" tra le parole \"martedì\", \"giovedì\", \"domenica\", \"sabato\" e \"argento\"?"
  },
  {
    "id": "1973",
    "input": "Qual è la parola più correlata con la categoria \"parenti\" tra le parole \"riproduzione\", \"morte\", \"specie\", \"figlia\" e \"essere\"?"
  },
  {
    "id": "2005",
    "input": "Tra le seguenti parole, scegli la parola più comunemente associata con la categoria \"termini socio-politici\" - \"chiave\", \"martello\", \"dipartimento\", \"cavo\", \"telecamera\":"
  },
  {
    "id": "2047",
    "input": "Tra le seguenti parole, scegli la parola più comunemente associata con la categoria \"verbi di movimento\" - \"adulto\", \"donna\", \"andare\", \"adulta\", \"bimba\":"
  },
  {
    "id": "2048",
    "input": "Tra le seguenti parole, scegli la parola più comunemente associata con la categoria \"misure\" - \"accettare\", \"bere\", \"aspettare\", \"trovare\", \"millilitro\":"
  },
  {
    "id": "2133",
    "input": "Tra le seguenti parole, scegli la parola più comunemente associata con la categoria \"misure\" - \"dittatura\", \"diritti\", \"paese\", \"città\", \"chilometro\":"
  },
  {
    "id": "2135",
    "input": "Tra le seguenti parole, scegli la parola più comunemente associata con la categoria \"strumenti musicali\" - \"pianoforte\", \"da\", \"con\", \"durante\", \"fino\":"
  },
  {
    "id": "2148",
    "input": "Tra le seguenti parole, scegli la parola più comunemente associata con la categoria \"aggettivi numerali ordinali\" - \"equitazione\", \"padel\", \"calcio\", \"centesimo\", \"rugby\":"
  },
  {
    "id": "2170",
    "input": "Tra le seguenti parole, scegli la parola più comunemente associata con la categoria \"aggettivi possessivi\" - \"mio\", \"vivere\", \"sparire\", \"crescere\", \"apparire\":"
  },
  {
    "id": "2238",
    "input": "Tra le seguenti parole, scegli la parola più comunemente associata con la categoria \"aggettivi possessivi\" - \"nonostante\", \"come\", \"ovvero\", \"e\", \"mio\":"
  },
  {
    "id": "2274",
    "input": "Tra le seguenti parole, scegli la parola più comunemente associata con la categoria \"materiali\" - \"umanità\", \"uomo\", \"neonato\", \"gente\", \"sale\":"
  },
  {
    "id": "2323",
    "input": "Tra le seguenti parole, scegli la parola più comunemente associata con la categoria \"catastrofe naturale\" - \"suo\", \"nostro\", \"tuo\", \"mio\", \"valanga\":"
  },
  {
    "id": "2502",
    "input": "Tra le seguenti parole, scegli la parola più comunemente associata con la categoria \"aggettivi qualificativi\" - \"ampio\", \"spesso\", \"solito\", \"compatto\", \"piccolo\":"
  },
  {
    "id": "2505",
    "input": "Tra le seguenti parole, scegli la parola più comunemente associata con la categoria \"avverbi opinativi\" - \"percepire\", \"difficilmente\", \"udire\", \"toccare\", \"fiutare\":"
  },
  {
    "id": "2597",
    "input": "Tra le seguenti parole, scegli la parola più comunemente associata con la categoria \"aggettivi sensoriali\" - \"palude\", \"inebriante\", \"canale\", \"valle\", \"scarpata\":"
  },
  {
    "id": "2605",
    "input": "Tra le seguenti parole, scegli la parola più comunemente associata con la categoria \"colori\" - \"bianco\", \"presto\", \"prima\", \"domani\", \"oggi\":"
  },
  {
    "id": "2641",
    "input": "Tra le seguenti parole, scegli la parola più comunemente associata con la categoria \"aggettivi numerali ordinali\" - \"oreficeria\", \"primo\", \"macelleria\", \"hotel\", \"bar\":"
  },
  {
    "id": "2642",
    "input": "Tra le seguenti parole, scegli la parola più comunemente associata con la categoria \"verbi di esistenza\" - \"rattristarsi\", \"rallegrarsi\", \"annoiarsi\", \"consolare\", \"crescere\":"
  },
  {
    "id": "2650",
    "input": "Tra le seguenti parole, scegli la parola più comunemente associata con la categoria \"verbi di esistenza\" - \"tardi\", \"crescere\", \"comunque\", \"mentre\", \"ancora\":"
  },
  {
    "id": "2678",
    "input": "Tra le seguenti parole, scegli la parola più comunemente associata con la categoria \"avverbi opinativi\" - \"giugno\", \"possibilmente\", \"marzo\", \"ottobre\", \"gennaio\":"
  },
  {
    "id": "2729",
    "input": "Tra le seguenti parole, scegli la parola più comunemente associata con la categoria \"vestiti\" - \"calze\", \"scarpata\", \"giungla\", \"lago\", \"foresta\":"
  },
  {
    "id": "2732",
    "input": "Tra le seguenti parole, scegli la parola più comunemente associata con la categoria \"verbi di esistenza\" - \"idraulico\", \"politico\", \"architetto\", \"giudice\", \"crescere\":"
  },
  {
    "id": "2757",
    "input": "Tra le seguenti parole, scegli la parola più comunemente associata con la categoria \"congiunzioni\" - \"né\", \"nonno\", \"cugino\", \"suocera\", \"sposo\":"
  },
  {
    "id": "2827",
    "input": "Tra le seguenti parole, scegli la parola più comunemente associata con la categoria \"sport\" - \"deputato\", \"idraulico\", \"giornalista\", \"ciclismo\", \"macellaio\":"
  },
  {
    "id": "2916",
    "input": "Tra le seguenti parole, scegli la parola più comunemente associata con la categoria \"materiali\" - \"traffico\", \"strada\", \"ghiaccio\", \"treno\", \"rotaia\":"
  },
  {
    "id": "2930",
    "input": "Tra le seguenti parole, scegli la parola più comunemente associata con la categoria \"avverbi opinativi\" - \"mai\", \"fune\", \"telecamera\", \"ago\", \"cucchiaino\":"
  }
]