[
  {
    "id": "41",
    "input": "\"baina\", \"nahiz\", \"ezpada\", \"orduan\" eta \"eta\" hitzetako guztiak juntagailu edo menderagailuak dira? Erantzun \"bai\" edo \"ez\"."
  },
  {
    "id": "88",
    "input": "\"arto\", \"zerba\", \"azalore\", \"orburu\" eta \"baratxuri\" hitzetako guztiak barazkiak dira? Erantzun \"bai\" edo \"ez\"."
  },
  {
    "id": "105",
    "input": "\"agertu\", \"izan\", \"existitu\", \"desagertu\" eta \"hil\" hitzetako guztiak existentzia aditzak dira? Erantzun \"bai\" edo \"ez\"."
  },
  {
    "id": "161",
    "input": "\"aurre\", \"barne\", \"ordez\", \"kanpo\" eta \"gain\" hitzetako guztiak postposizio askeak dira? Erantzun \"bai\" edo \"ez\"."
  },
  {
    "id": "366",
    "input": "\"oker\", \"zahar\", \"berdin\", \"arestiko\" eta \"nagusi\" hitzetako guztiak kalitate adjektiboak dira? Erantzun \"bai\" edo \"ez\"."
  },
  {
    "id": "562",
    "input": "\"sute\", \"lurrikara\", \"urakan\", \"tsunami\" eta \"tornado\" hitzetako guztiak hondamendi naturalak dira? Erantzun \"bai\" edo \"ez\"."
  },
  {
    "id": "579",
    "input": "\"su\", \"metal\", \"aire\", \"urre\" eta \"berun\" hitzetako guztiak materialak dira? Erantzun \"bai\" edo \"ez\"."
  },
  {
    "id": "596",
    "input": "\"kuiatxo\", \"ilarrak\", \"brokoli\", \"erremolatxa\" eta \"espinaka\" hitzetako guztiak barazkiak dira? Erantzun \"bai\" edo \"ez\"."
  },
  {
    "id": "890",
    "input": "\"itsasalde\", \"natura\", \"ozeano\", \"hondartza\" eta \"mendi\" hitzetako guztiak geografiarekin zerikusia duten hitzak dira? Erantzun \"bai\" edo \"ez\"."
  },
  {
    "id": "940",
    "input": "\"etxe\", \"etxebizitza\", \"panel\", \"mahai\" eta \"sabai\" hitzetako guztiak etxearekin zerikusia duten hitzak dira? Erantzun \"bai\" edo \"ez\"."
  },
  {
    "id": "967",
    "input": "\"justu\", \"hainbeste\", \"apenas\", \"ia\" eta \"nahiko\" hitzetako guztiak kantitate-aditzondoak dira? Erantzun \"bai\" edo \"ez\"."
  },
  {
    "id": "1022",
    "input": "\"bada\", \"ezpada\", \"eta\", \"baina\" eta \"ezik\" hitzetako guztiek juntagailu edo menderagailuak adierazten dituzte? Erantzun \"bai\" edo \"ez\"."
  },
  {
    "id": "1153",
    "input": "\"dama\", \"gizaki\", \"nerabe\", \"andre\" eta \"jaun\" hitzetako guztiek jendearekin zerikusia duten hitzak adierazten dituzte? Erantzun \"bai\" edo \"ez\"."
  },
  {
    "id": "1319",
    "input": "\"biolin\", \"saxofoi\", \"bateria\", \"piano\" eta \"gitarra\" hitzetako guztiek instrumentuak adierazten dituzte? Erantzun \"bai\" edo \"ez\"."
  },
  {
    "id": "1450",
    "input": "\"nekez\", \"seguruenik\", \"beharbada\", \"agian\" eta \"aise\" hitzetako guztiek iritzi-aditzondoak adierazten dituzte? Erantzun \"bai\" edo \"ez\"."
  },
  {
    "id": "1501",
    "input": "\"lagun\", \"birramona\", \"lehengusina\", \"senar\" eta \"birbiloba\" hitzetako guztiek familiarekin zerikusia duten hitzak adierazten dituzte? Erantzun \"bai\" edo \"ez\"."
  },
  {
    "id": "1783",
    "input": "\"interes\", \"egitasmo\", \"izen\", \"jarrera\" eta \"esanahi\" hitzetako guztiek izen abstraktuak adierazten dituzte? Erantzun \"bai\" edo \"ez\"."
  },
  {
    "id": "1796",
    "input": "\"laranja\", \"kolore\", \"arrosa\", \"berde\" eta \"beltz\" hitzetako guztiek koloreak adierazten dituzte? Erantzun \"bai\" edo \"ez\"."
  },
  {
    "id": "1902",
    "input": "\"laranja\", \"berde\", \"arrosa\", \"zuri\" eta \"marroi\" hitzetako guztiek koloreak adierazten dituzte? Erantzun \"bai\" edo \"ez\"."
  },
  {
    "id": "2005",
    "input": "[\"azaro\", \"ekain\", \"irail\", \"abendu\", \"otsail\"] zerrendak hilabeteak besterik ez ditu? Erantzun \"bai\" edo \"ez\"."
  },
  {
    "id": "2047",
    "input": "[\"bereziki\", \"astiro\", \"azkenik\", \"hobeto\", \"azkar\"] zerrendak modu-aditzondoak besterik ez ditu? Erantzun \"bai\" edo \"ez\"."
  },
  {
    "id": "2048",
    "input": "[\"kontsolatu\", \"aspertu\", \"haserretu\", \"gorrotatu\", \"desiratu\"] zerrendak emozio aditzak besterik ez ditu? Erantzun \"bai\" edo \"ez\"."
  },
  {
    "id": "2135",
    "input": "[\"trinko\", \"lodi\", \"handi\", \"txiki\", \"estu\"] zerrendak forma izenondoak besterik ez ditu? Erantzun \"bai\" edo \"ez\"."
  },
  {
    "id": "2170",
    "input": "[\"miretsi\", \"desiratu\", \"interesatu\", \"nahigabetu\", \"liluratu\"] zerrendak emozio aditzak besterik ez ditu? Erantzun \"bai\" edo \"ez\"."
  },
  {
    "id": "2238",
    "input": "[\"interesatu\", \"harritu\", \"gorrotatu\", \"kontsolatu\", \"poztu\"] zerrendak emozio aditzak besterik ez ditu? Erantzun \"bai\" edo \"ez\"."
  },
  {
    "id": "2605",
    "input": "[\"eta\", \"baina\", \"orduan\", \"bada\", \"nahiz\"] zerrendak juntagailu edo menderagailuak besterik ez ditu? Erantzun \"bai\" edo \"ez\"."
  },
  {
    "id": "2650",
    "input": "[\"ekain\", \"uztail\", \"urtarril\", \"urri\", \"otsail\"] zerrendak hilabeteak besterik ez ditu? Erantzun \"bai\" edo \"ez\"."
  },
  {
    "id": "2678",
    "input": "[\"galtzerdiak\", \"itxigailu\", \"tapauka\", \"mahuka\", \"eskularruak\"] zerrendak jantziak besterik ez ditu? Erantzun \"bai\" edo \"ez\"."
  },
  {
    "id": "2732",
    "input": "[\"igande\", \"ostegun\", \"astearte\", \"asteazken\", \"astelehen\"] zerrendak asteko egunak besterik ez ditu? Erantzun \"bai\" edo \"ez\"."
  },
  {
    "id": "2827",
    "input": "[\"batere\", \"asko\", \"nahiko\", \"apenas\", \"gehiago\"] zerrendak kantitate-aditzondoak besterik ez ditu? Erantzun \"bai\" edo \"ez\"."
  }
]