[
  {
    "id": "5",
    "input": "Idatzi \"ostikatu\" hitzarekin hasten den esaldi bat:"
  },
  {
    "id": "7",
    "input": "Idatzi \"apurtu\" hitzarekin hasten den esaldi bat:"
  },
  {
    "id": "8",
    "input": "Idatzi \"isildu\" hitzarekin hasten den esaldi bat:"
  },
  {
    "id": "12",
    "input": "Idatzi \"irakurri\" hitzarekin hasten den esaldi bat:"
  },
  {
    "id": "22",
    "input": "Idatzi \"sentitu\" hitzarekin hasten den esaldi bat:"
  },
  {
    "id": "27",
    "input": "Idatzi \"ulertu\" hitzarekin hasten den esaldi bat:"
  },
  {
    "id": "38",
    "input": "Idatzi \"desiratu\" hitzarekin hasten den esaldi bat:"
  },
  {
    "id": "42",
    "input": "Idatzi \"arte\" hitzarekin hasten den esaldi bat:"
  },
  {
    "id": "46",
    "input": "Idatzi \"bereizi\" hitzarekin hasten den esaldi bat:"
  },
  {
    "id": "51",
    "input": "Idatzi \"landu\" hitzarekin hasten den esaldi bat:"
  },
  {
    "id": "54",
    "input": "Idatzi \"gain\" hitzarekin hasten den esaldi bat:"
  },
  {
    "id": "60",
    "input": "Idatzi \"baztertu\" hitzarekin hasten den esaldi bat:"
  },
  {
    "id": "73",
    "input": "Idatzi \"gogoratu\" hitzarekin hasten den esaldi bat:"
  },
  {
    "id": "75",
    "input": "Idatzi \"ikaratu\" hitzarekin hasten den esaldi bat:"
  },
  {
    "id": "89",
    "input": "Idatzi \"edan\" hitzarekin hasten den esaldi bat:"
  },
  {
    "id": "90",
    "input": "Idatzi \"erantsi\" hitzarekin hasten den esaldi bat:"
  },
  {
    "id": "93",
    "input": "Idatzi \"hazi\" hitzarekin hasten den esaldi bat:"
  },
  {
    "id": "94",
    "input": "Idatzi \"okerragotu\" hitzarekin hasten den esaldi bat:"
  },
  {
    "id": "95",
    "input": "Idatzi \"konpondu\" hitzarekin hasten den esaldi bat:"
  },
  {
    "id": "96",
    "input": "Idatzi \"barne\" hitzarekin hasten den esaldi bat:"
  },
  {
    "id": "97",
    "input": "Idatzi \"tolestu\" hitzarekin hasten den esaldi bat:"
  },
  {
    "id": "101",
    "input": "Idatzi \"abestu\" hitzarekin hasten den esaldi bat:"
  },
  {
    "id": "110",
    "input": "Idatzi \"iruditu\" hitzarekin hasten den esaldi bat:"
  },
  {
    "id": "121",
    "input": "Idatzi \"atera\" hitzarekin hasten den esaldi bat:"
  },
  {
    "id": "128",
    "input": "Idatzi \"arabera\" hitzarekin hasten den esaldi bat:"
  },
  {
    "id": "130",
    "input": "Idatzi \"tratatu\" hitzarekin hasten den esaldi bat:"
  },
  {
    "id": "133",
    "input": "Idatzi \"izan\" hitzarekin hasten den esaldi bat:"
  },
  {
    "id": "142",
    "input": "Idatzi \"egotzi\" hitzarekin hasten den esaldi bat:"
  },
  {
    "id": "145",
    "input": "Idatzi \"neurtu\" hitzarekin hasten den esaldi bat:"
  },
  {
    "id": "152",
    "input": "Idatzi \"elkartu\" hitzarekin hasten den esaldi bat:"
  },
  {
    "id": "163",
    "input": "Idatzi \"desagertu\" hitzarekin hasten den esaldi bat:"
  },
  {
    "id": "164",
    "input": "Idatzi \"ordez\" hitzarekin hasten den esaldi bat:"
  },
  {
    "id": "165",
    "input": "Idatzi \"aurre\" hitzarekin hasten den esaldi bat:"
  },
  {
    "id": "176",
    "input": "Idatzi esaldi bat zeinen lehenengo hitza \"esnatu\" den:"
  },
  {
    "id": "181",
    "input": "Idatzi esaldi bat zeinen lehenengo hitza \"sinetsi\" den:"
  },
  {
    "id": "185",
    "input": "Idatzi esaldi bat zeinen lehenengo hitza \"aldatu\" den:"
  },
  {
    "id": "189",
    "input": "Idatzi esaldi bat zeinen lehenengo hitza \"seinalatu\" den:"
  },
  {
    "id": "197",
    "input": "Idatzi esaldi bat zeinen lehenengo hitza \"aurreratu\" den:"
  },
  {
    "id": "204",
    "input": "Idatzi esaldi bat zeinen lehenengo hitza \"iritsi\" den:"
  },
  {
    "id": "208",
    "input": "Idatzi esaldi bat zeinen lehenengo hitza \"deskantsatu\" den:"
  },
  {
    "id": "209",
    "input": "Idatzi esaldi bat zeinen lehenengo hitza \"ekarri\" den:"
  },
  {
    "id": "211",
    "input": "Idatzi esaldi bat zeinen lehenengo hitza \"bereizi\" den:"
  },
  {
    "id": "219",
    "input": "Idatzi esaldi bat zeinen lehenengo hitza \"gain\" den:"
  },
  {
    "id": "231",
    "input": "Idatzi esaldi bat zeinen lehenengo hitza \"joan\" den:"
  },
  {
    "id": "234",
    "input": "Idatzi esaldi bat zeinen lehenengo hitza \"laga\" den:"
  },
  {
    "id": "243",
    "input": "Idatzi esaldi bat zeinen lehenengo hitza \"lagundu\" den:"
  },
  {
    "id": "245",
    "input": "Idatzi esaldi bat zeinen lehenengo hitza \"abiatu\" den:"
  },
  {
    "id": "246",
    "input": "Idatzi esaldi bat zeinen lehenengo hitza \"bizi\" den:"
  },
  {
    "id": "247",
    "input": "Idatzi esaldi bat zeinen lehenengo hitza \"erdi\" den:"
  },
  {
    "id": "248",
    "input": "Idatzi esaldi bat zeinen lehenengo hitza \"jarraitu\" den:"
  },
  {
    "id": "254",
    "input": "Idatzi esaldi bat zeinen lehenengo hitza \"edan\" den:"
  },
  {
    "id": "268",
    "input": "Idatzi esaldi bat zeinen lehenengo hitza \"atzitu\" den:"
  },
  {
    "id": "269",
    "input": "Idatzi esaldi bat zeinen lehenengo hitza \"sastatu\" den:"
  },
  {
    "id": "270",
    "input": "Idatzi esaldi bat zeinen lehenengo hitza \"gabe\" den:"
  },
  {
    "id": "278",
    "input": "Idatzi esaldi bat zeinen lehenengo hitza \"hausnartu\" den:"
  },
  {
    "id": "292",
    "input": "Idatzi esaldi bat zeinen lehenengo hitza \"aztertu\" den:"
  },
  {
    "id": "293",
    "input": "Idatzi esaldi bat zeinen lehenengo hitza \"arabera\" den:"
  },
  {
    "id": "297",
    "input": "Idatzi esaldi bat zeinen lehenengo hitza \"gehitu\" den:"
  },
  {
    "id": "301",
    "input": "Idatzi esaldi bat zeinen lehenengo hitza \"atzeratu\" den:"
  },
  {
    "id": "308",
    "input": "Idatzi esaldi bat zeinen lehenengo hitza \"agertu\" den:"
  },
  {
    "id": "319",
    "input": "Idatzi esaldi bat zeinen lehenengo hitza \"barik\" den:"
  },
  {
    "id": "329",
    "input": "Idatzi esaldi bat zeinen lehenengo hitza \"ordez\" den:"
  },
  {
    "id": "337",
    "input": "Idatzi esaldi bat \"apurtu\" hitzarekin hasita:"
  },
  {
    "id": "341",
    "input": "Idatzi esaldi bat \"esnatu\" hitzarekin hasita:"
  },
  {
    "id": "354",
    "input": "Idatzi esaldi bat \"seinalatu\" hitzarekin hasita:"
  },
  {
    "id": "363",
    "input": "Idatzi esaldi bat \"lortu\" hitzarekin hasita:"
  },
  {
    "id": "364",
    "input": "Idatzi esaldi bat \"poztu\" hitzarekin hasita:"
  },
  {
    "id": "365",
    "input": "Idatzi esaldi bat \"ikusi\" hitzarekin hasita:"
  },
  {
    "id": "369",
    "input": "Idatzi esaldi bat \"iritsi\" hitzarekin hasita:"
  },
  {
    "id": "379",
    "input": "Idatzi esaldi bat \"baieztatu\" hitzarekin hasita:"
  },
  {
    "id": "384",
    "input": "Idatzi esaldi bat \"gain\" hitzarekin hasita:"
  },
  {
    "id": "385",
    "input": "Idatzi esaldi bat \"ireki\" hitzarekin hasita:"
  },
  {
    "id": "390",
    "input": "Idatzi esaldi bat \"baztertu\" hitzarekin hasita:"
  },
  {
    "id": "393",
    "input": "Idatzi esaldi bat \"erabili\" hitzarekin hasita:"
  },
  {
    "id": "394",
    "input": "Idatzi esaldi bat \"antzeman\" hitzarekin hasita:"
  },
  {
    "id": "403",
    "input": "Idatzi esaldi bat \"gogoratu\" hitzarekin hasita:"
  },
  {
    "id": "404",
    "input": "Idatzi esaldi bat \"eman\" hitzarekin hasita:"
  },
  {
    "id": "411",
    "input": "Idatzi esaldi bat \"bizi\" hitzarekin hasita:"
  },
  {
    "id": "424",
    "input": "Idatzi esaldi bat \"okerragotu\" hitzarekin hasita:"
  },
  {
    "id": "428",
    "input": "Idatzi esaldi bat \"ezagutu\" hitzarekin hasita:"
  },
  {
    "id": "433",
    "input": "Idatzi esaldi bat \"atzitu\" hitzarekin hasita:"
  },
  {
    "id": "435",
    "input": "Idatzi esaldi bat \"gabe\" hitzarekin hasita:"
  },
  {
    "id": "441",
    "input": "Idatzi esaldi bat \"trukatu\" hitzarekin hasita:"
  },
  {
    "id": "449",
    "input": "Idatzi esaldi bat \"eraman\" hitzarekin hasita:"
  },
  {
    "id": "453",
    "input": "Idatzi esaldi bat \"idatzi\" hitzarekin hasita:"
  },
  {
    "id": "461",
    "input": "Idatzi esaldi bat \"erkatu\" hitzarekin hasita:"
  },
  {
    "id": "464",
    "input": "Idatzi esaldi bat \"zaildu\" hitzarekin hasita:"
  },
  {
    "id": "468",
    "input": "Idatzi esaldi bat \"nahigabetu\" hitzarekin hasita:"
  },
  {
    "id": "475",
    "input": "Idatzi esaldi bat \"neurtu\" hitzarekin hasita:"
  }
]