[
  {
    "id": "41",
    "input": "Qual palavra tem mais letras: \"universal\" ou \"política\"?"
  },
  {
    "id": "88",
    "input": "Qual palavra tem mais letras: \"código\" ou \"valor\"?"
  },
  {
    "id": "105",
    "input": "Qual palavra tem mais letras: \"vestuário\" ou \"potência\"?"
  },
  {
    "id": "161",
    "input": "Qual palavra tem mais letras: \"água\" ou \"corte\"?"
  },
  {
    "id": "366",
    "input": "Qual palavra tem mais letras: \"lago\" ou \"costa\"?"
  },
  {
    "id": "562",
    "input": "Qual palavra tem mais letras: \"bunda\" ou \"grande\"?"
  },
  {
    "id": "579",
    "input": "Qual palavra tem mais letras: \"centésimo\" ou \"brócolis\"?"
  },
  {
    "id": "596",
    "input": "Qual palavra tem mais letras: \"fechar\" ou \"romance\"?"
  },
  {
    "id": "890",
    "input": "Qual palavra tem mais letras: \"litro\" ou \"nascer\"?"
  },
  {
    "id": "940",
    "input": "Qual palavra tem mais letras: \"senador\" ou \"urbano\"?"
  },
  {
    "id": "967",
    "input": "Qual palavra tem mais letras: \"boné\" ou \"então\"?"
  },
  {
    "id": "1022",
    "input": "Qual palavra é mais longa: \"resultado\" ou \"hospital\"?"
  },
  {
    "id": "1153",
    "input": "Qual palavra é mais longa: \"automóvel\" ou \"quilômetro\"?"
  },
  {
    "id": "1319",
    "input": "Qual palavra é mais longa: \"setor\" ou \"vida\"?"
  },
  {
    "id": "1450",
    "input": "Qual palavra é mais longa: \"junho\" ou \"pintor\"?"
  },
  {
    "id": "1501",
    "input": "Qual palavra é mais longa: \"socar\" ou \"sapo\"?"
  },
  {
    "id": "1783",
    "input": "Qual palavra é mais longa: \"pedir\" ou \"marido\"?"
  },
  {
    "id": "1796",
    "input": "Qual palavra é mais longa: \"comédia\" ou \"suéter\"?"
  },
  {
    "id": "1902",
    "input": "Qual palavra é mais longa: \"chumbo\" ou \"pesar\"?"
  },
  {
    "id": "2005",
    "input": "Das palavras \"penúltimo\" e \"quilômetro\", qual tem mais letras?"
  },
  {
    "id": "2047",
    "input": "Das palavras \"explicar\" e \"vestuário\", qual tem mais letras?"
  },
  {
    "id": "2048",
    "input": "Das palavras \"destruição\" e \"sequência\", qual tem mais letras?"
  },
  {
    "id": "2135",
    "input": "Das palavras \"ovelha\" e \"comédia\", qual tem mais letras?"
  },
  {
    "id": "2170",
    "input": "Das palavras \"chegar\" e \"mosca\", qual tem mais letras?"
  },
  {
    "id": "2238",
    "input": "Das palavras \"serviço\" e \"patins\", qual tem mais letras?"
  },
  {
    "id": "2605",
    "input": "Das palavras \"problema\" e \"resultado\", qual tem mais letras?"
  },
  {
    "id": "2650",
    "input": "Das palavras \"banheiro\" e \"atenção\", qual tem mais letras?"
  },
  {
    "id": "2678",
    "input": "Das palavras \"universal\" e \"adjetivo\", qual tem mais letras?"
  },
  {
    "id": "2732",
    "input": "Das palavras \"pasto\" e \"égua\", qual tem mais letras?"
  },
  {
    "id": "2827",
    "input": "Das palavras \"ônibus\" e \"comer\", qual tem mais letras?"
  }
]