[
  {
    "id": "1",
    "input": "Escreva uma frase que contenha a palavra \"esperar\":"
  },
  {
    "id": "22",
    "input": "Escreva uma frase que contenha a palavra \"menina\":"
  },
  {
    "id": "37",
    "input": "Escreva uma frase que contenha a palavra \"consciência\":"
  },
  {
    "id": "41",
    "input": "Escreva uma frase que contenha a palavra \"ler\":"
  },
  {
    "id": "46",
    "input": "Escreva uma frase que contenha a palavra \"musical\":"
  },
  {
    "id": "65",
    "input": "Escreva uma frase que contenha a palavra \"fantasia\":"
  },
  {
    "id": "88",
    "input": "Escreva uma frase que contenha a palavra \"rejeitar\":"
  },
  {
    "id": "105",
    "input": "Escreva uma frase que contenha a palavra \"prefeitura\":"
  },
  {
    "id": "161",
    "input": "Escreva uma frase que contenha a palavra \"mecânico\":"
  },
  {
    "id": "183",
    "input": "Escreva uma frase que contenha a palavra \"grave\":"
  },
  {
    "id": "201",
    "input": "Escreva uma frase que contenha a palavra \"triste\":"
  },
  {
    "id": "244",
    "input": "Escreva uma frase que contenha a palavra \"cientista\":"
  },
  {
    "id": "252",
    "input": "Escreva uma frase que contenha a palavra \"acerto\":"
  },
  {
    "id": "266",
    "input": "Escreva uma frase que contenha a palavra \"amarelo\":"
  },
  {
    "id": "288",
    "input": "Escreva uma frase que contenha a palavra \"preposição\":"
  },
  {
    "id": "320",
    "input": "Escreva uma frase que contenha a palavra \"semelhança\":"
  },
  {
    "id": "350",
    "input": "Escreva uma frase que contenha a palavra \"contrabaixo\":"
  },
  {
    "id": "366",
    "input": "Escreva uma frase que contenha a palavra \"sardinha\":"
  },
  {
    "id": "367",
    "input": "Escreva uma frase que contenha a palavra \"rodovia\":"
  },
  {
    "id": "385",
    "input": "Escreva uma frase que contenha a palavra \"agulha\":"
  },
  {
    "id": "401",
    "input": "Escreva uma frase que contenha a palavra \"pessoa\":"
  },
  {
    "id": "431",
    "input": "Escreva uma frase que contenha a palavra \"dano\":"
  },
  {
    "id": "447",
    "input": "Escreva uma frase que contenha a palavra \"nacional\":"
  },
  {
    "id": "477",
    "input": "Escreva uma frase que contenha a palavra \"lesma\":"
  },
  {
    "id": "533",
    "input": "Escreva uma frase que contenha a palavra \"biólogo\":"
  },
  {
    "id": "535",
    "input": "Escreva uma frase que contenha a palavra \"certo\":"
  },
  {
    "id": "538",
    "input": "Escreva uma frase que contenha a palavra \"talvez\":"
  },
  {
    "id": "541",
    "input": "Escreva uma frase que contenha a palavra \"até\":"
  },
  {
    "id": "562",
    "input": "Escreva uma frase que contenha a palavra \"princípio\":"
  },
  {
    "id": "579",
    "input": "Escreva uma frase que contenha a palavra \"halterofilismo\":"
  },
  {
    "id": "594",
    "input": "Escreva uma frase que contenha a palavra \"consequência\":"
  },
  {
    "id": "596",
    "input": "Escreva uma frase que contenha a palavra \"comum\":"
  },
  {
    "id": "610",
    "input": "Escreva uma frase que contenha a palavra \"significado\":"
  },
  {
    "id": "650",
    "input": "Escreva uma frase que contenha a palavra \"igual\":"
  },
  {
    "id": "691",
    "input": "Escreva uma frase que contenha a palavra \"mostrar\":"
  },
  {
    "id": "709",
    "input": "Escreva uma frase que contenha a palavra \"começar\":"
  },
  {
    "id": "724",
    "input": "Escreva uma frase que contenha a palavra \"interessado\":"
  },
  {
    "id": "763",
    "input": "Escreva uma frase que contenha a palavra \"óbvio\":"
  },
  {
    "id": "795",
    "input": "Escreva uma frase que contenha a palavra \"janela\":"
  },
  {
    "id": "827",
    "input": "Escreva uma frase que contenha a palavra \"juiz\":"
  },
  {
    "id": "832",
    "input": "Escreva uma frase que contenha a palavra \"falta\":"
  },
  {
    "id": "843",
    "input": "Escreva uma frase que contenha a palavra \"mas\":"
  },
  {
    "id": "890",
    "input": "Escreva uma frase que contenha a palavra \"furacão\":"
  },
  {
    "id": "940",
    "input": "Escreva uma frase que contenha a palavra \"ali\":"
  },
  {
    "id": "958",
    "input": "Escreva uma frase que contenha a palavra \"ataque\":"
  },
  {
    "id": "967",
    "input": "Escreva uma frase que contenha a palavra \"desejar\":"
  },
  {
    "id": "979",
    "input": "Escreva uma frase que contenha a palavra \"antes\":"
  },
  {
    "id": "993",
    "input": "Escreva uma frase que contenha a palavra \"segurar\":"
  },
  {
    "id": "1022",
    "input": "Escreva uma frase usando a palavra \"menina\":"
  },
  {
    "id": "1048",
    "input": "Escreva uma frase usando a palavra \"rural\":"
  },
  {
    "id": "1053",
    "input": "Escreva uma frase usando a palavra \"potência\":"
  },
  {
    "id": "1055",
    "input": "Escreva uma frase usando a palavra \"nome\":"
  },
  {
    "id": "1063",
    "input": "Escreva uma frase usando a palavra \"frontal\":"
  },
  {
    "id": "1072",
    "input": "Escreva uma frase usando a palavra \"tigre\":"
  },
  {
    "id": "1108",
    "input": "Escreva uma frase usando a palavra \"gerar\":"
  },
  {
    "id": "1135",
    "input": "Escreva uma frase usando a palavra \"irritado\":"
  },
  {
    "id": "1148",
    "input": "Escreva uma frase usando a palavra \"constituição\":"
  },
  {
    "id": "1153",
    "input": "Escreva uma frase usando a palavra \"litro\":"
  },
  {
    "id": "1205",
    "input": "Escreva uma frase usando a palavra \"exceto\":"
  },
  {
    "id": "1210",
    "input": "Escreva uma frase usando a palavra \"milho\":"
  },
  {
    "id": "1232",
    "input": "Escreva uma frase usando a palavra \"encontrar\":"
  },
  {
    "id": "1237",
    "input": "Escreva uma frase usando a palavra \"pesado\":"
  },
  {
    "id": "1259",
    "input": "Escreva uma frase usando a palavra \"trazer\":"
  },
  {
    "id": "1268",
    "input": "Escreva uma frase usando a palavra \"yoga\":"
  },
  {
    "id": "1319",
    "input": "Escreva uma frase usando a palavra \"cheirar\":"
  },
  {
    "id": "1343",
    "input": "Escreva uma frase usando a palavra \"resultado\":"
  },
  {
    "id": "1384",
    "input": "Escreva uma frase usando a palavra \"tamanho\":"
  },
  {
    "id": "1408",
    "input": "Escreva uma frase usando a palavra \"alegria\":"
  },
  {
    "id": "1428",
    "input": "Escreva uma frase usando a palavra \"tomar\":"
  },
  {
    "id": "1437",
    "input": "Escreva uma frase usando a palavra \"esgrima\":"
  },
  {
    "id": "1444",
    "input": "Escreva uma frase usando a palavra \"selva\":"
  },
  {
    "id": "1450",
    "input": "Escreva uma frase usando a palavra \"azul\":"
  },
  {
    "id": "1462",
    "input": "Escreva uma frase usando a palavra \"aldeia\":"
  },
  {
    "id": "1470",
    "input": "Escreva uma frase usando a palavra \"progresso\":"
  },
  {
    "id": "1473",
    "input": "Escreva uma frase usando a palavra \"amar\":"
  },
  {
    "id": "1491",
    "input": "Escreva uma frase usando a palavra \"rápido\":"
  },
  {
    "id": "1501",
    "input": "Escreva uma frase usando a palavra \"enquanto\":"
  },
  {
    "id": "1503",
    "input": "Escreva uma frase usando a palavra \"necessário\":"
  },
  {
    "id": "1506",
    "input": "Escreva uma frase usando a palavra \"óculos\":"
  },
  {
    "id": "1519",
    "input": "Escreva uma frase usando a palavra \"ficar\":"
  },
  {
    "id": "1536",
    "input": "Escreva uma frase usando a palavra \"bonde\":"
  },
  {
    "id": "1587",
    "input": "Escreva uma frase usando a palavra \"frio\":"
  },
  {
    "id": "1660",
    "input": "Escreva uma frase usando a palavra \"amiga\":"
  },
  {
    "id": "1677",
    "input": "Escreva uma frase usando a palavra \"mal\":"
  },
  {
    "id": "1728",
    "input": "Escreva uma frase usando a palavra \"milionésimo\":"
  },
  {
    "id": "1751",
    "input": "Escreva uma frase usando a palavra \"sem\":"
  },
  {
    "id": "1777",
    "input": "Escreva uma frase usando a palavra \"jamais\":"
  },
  {
    "id": "1783",
    "input": "Escreva uma frase usando a palavra \"atirar\":"
  },
  {
    "id": "1793",
    "input": "Escreva uma frase usando a palavra \"veículo\":"
  },
  {
    "id": "1796",
    "input": "Escreva uma frase usando a palavra \"berinjela\":"
  },
  {
    "id": "1819",
    "input": "Escreva uma frase usando a palavra \"contente\":"
  },
  {
    "id": "1832",
    "input": "Escreva uma frase usando a palavra \"falta\":"
  },
  {
    "id": "1875",
    "input": "Escreva uma frase usando a palavra \"aranha\":"
  },
  {
    "id": "1902",
    "input": "Escreva uma frase usando a palavra \"regional\":"
  },
  {
    "id": "1932",
    "input": "Escreva uma frase usando a palavra \"unha\":"
  },
  {
    "id": "1942",
    "input": "Escreva uma frase usando a palavra \"bisneto\":"
  },
  {
    "id": "1967",
    "input": "Escreva uma frase usando a palavra \"desejar\":"
  },
  {
    "id": "1971",
    "input": "Escreva uma frase usando a palavra \"joelho\":"
  },
  {
    "id": "1973",
    "input": "Escreva uma frase usando a palavra \"entrevistar\":"
  },
  {
    "id": "2005",
    "input": "Escreva uma frase com a palavra \"laranja\":"
  },
  {
    "id": "2043",
    "input": "Escreva uma frase com a palavra \"fundo\":"
  },
  {
    "id": "2047",
    "input": "Escreva uma frase com a palavra \"etapa\":"
  },
  {
    "id": "2048",
    "input": "Escreva uma frase com a palavra \"rural\":"
  },
  {
    "id": "2057",
    "input": "Escreva uma frase com a palavra \"carpinteiro\":"
  },
  {
    "id": "2084",
    "input": "Escreva uma frase com a palavra \"comunidade\":"
  },
  {
    "id": "2097",
    "input": "Escreva uma frase com a palavra \"problema\":"
  },
  {
    "id": "2098",
    "input": "Escreva uma frase com a palavra \"grosso\":"
  },
  {
    "id": "2133",
    "input": "Escreva uma frase com a palavra \"bicicleta\":"
  },
  {
    "id": "2135",
    "input": "Escreva uma frase com a palavra \"irritado\":"
  },
  {
    "id": "2148",
    "input": "Escreva uma frase com a palavra \"constituição\":"
  },
  {
    "id": "2157",
    "input": "Escreva uma frase com a palavra \"jovem\":"
  },
  {
    "id": "2164",
    "input": "Escreva uma frase com a palavra \"comprovar\":"
  },
  {
    "id": "2170",
    "input": "Escreva uma frase com a palavra \"tráfego\":"
  },
  {
    "id": "2238",
    "input": "Escreva uma frase com a palavra \"repolho\":"
  },
  {
    "id": "2242",
    "input": "Escreva uma frase com a palavra \"realidade\":"
  },
  {
    "id": "2274",
    "input": "Escreva uma frase com a palavra \"seca\":"
  },
  {
    "id": "2293",
    "input": "Escreva uma frase com a palavra \"anterior\":"
  },
  {
    "id": "2301",
    "input": "Escreva uma frase com a palavra \"afetar\":"
  },
  {
    "id": "2306",
    "input": "Escreva uma frase com a palavra \"seis\":"
  },
  {
    "id": "2323",
    "input": "Escreva uma frase com a palavra \"proibição\":"
  },
  {
    "id": "2369",
    "input": "Escreva uma frase com a palavra \"penúltimo\":"
  },
  {
    "id": "2396",
    "input": "Escreva uma frase com a palavra \"consumo\":"
  },
  {
    "id": "2409",
    "input": "Escreva uma frase com a palavra \"sequer\":"
  },
  {
    "id": "2446",
    "input": "Escreva uma frase com a palavra \"guerra\":"
  },
  {
    "id": "2480",
    "input": "Escreva uma frase com a palavra \"olho\":"
  },
  {
    "id": "2481",
    "input": "Escreva uma frase com a palavra \"programa\":"
  },
  {
    "id": "2500",
    "input": "Escreva uma frase com a palavra \"fotógrafo\":"
  },
  {
    "id": "2502",
    "input": "Escreva uma frase com a palavra \"espinafre\":"
  },
  {
    "id": "2505",
    "input": "Escreva uma frase com a palavra \"lugar\":"
  },
  {
    "id": "2507",
    "input": "Escreva uma frase com a palavra \"unido\":"
  },
  {
    "id": "2593",
    "input": "Escreva uma frase com a palavra \"pensar\":"
  },
  {
    "id": "2597",
    "input": "Escreva uma frase com a palavra \"cor\":"
  },
  {
    "id": "2605",
    "input": "Escreva uma frase com a palavra \"cobra\":"
  },
  {
    "id": "2612",
    "input": "Escreva uma frase com a palavra \"pedir\":"
  },
  {
    "id": "2640",
    "input": "Escreva uma frase com a palavra \"afastar\":"
  },
  {
    "id": "2641",
    "input": "Escreva uma frase com a palavra \"barro\":"
  },
  {
    "id": "2642",
    "input": "Escreva uma frase com a palavra \"demanda\":"
  },
  {
    "id": "2650",
    "input": "Escreva uma frase com a palavra \"igual\":"
  },
  {
    "id": "2678",
    "input": "Escreva uma frase com a palavra \"elevador\":"
  },
  {
    "id": "2729",
    "input": "Escreva uma frase com a palavra \"dinheiro\":"
  },
  {
    "id": "2732",
    "input": "Escreva uma frase com a palavra \"táxi\":"
  },
  {
    "id": "2757",
    "input": "Escreva uma frase com a palavra \"probabilidade\":"
  },
  {
    "id": "2820",
    "input": "Escreva uma frase com a palavra \"universal\":"
  },
  {
    "id": "2827",
    "input": "Escreva uma frase com a palavra \"juiz\":"
  },
  {
    "id": "2843",
    "input": "Escreva uma frase com a palavra \"mas\":"
  },
  {
    "id": "2850",
    "input": "Escreva uma frase com a palavra \"então\":"
  },
  {
    "id": "2865",
    "input": "Escreva uma frase com a palavra \"corda\":"
  },
  {
    "id": "2889",
    "input": "Escreva uma frase com a palavra \"construção\":"
  },
  {
    "id": "2916",
    "input": "Escreva uma frase com a palavra \"avô\":"
  },
  {
    "id": "2930",
    "input": "Escreva uma frase com a palavra \"absoluto\":"
  }
]