[
  {
    "id": "41",
    "input": "Totes les paraules \"empresa\", \"porta\", \"organització\", \"consell\" i \"comissió\" són conceptes de societat? Contesta exactament \"sí\" o \"no\"."
  },
  {
    "id": "88",
    "input": "Totes les paraules \"consell\", \"substantiu\", \"verb\", \"determinant\" i \"adverbi\" són categories gramaticals? Contesta exactament \"sí\" o \"no\"."
  },
  {
    "id": "105",
    "input": "Totes les paraules \"dimecres\", \"dilluns\", \"contingut\", \"divendres\" i \"dimarts\" són dies de la setmana? Contesta exactament \"sí\" o \"no\"."
  },
  {
    "id": "161",
    "input": "Totes les paraules \"taronja\", \"blau\", \"supermercat\", \"groc\" i \"color\" són colors? Contesta exactament \"sí\" o \"no\"."
  },
  {
    "id": "366",
    "input": "Totes les paraules \"reproducció\", \"ésser\", \"mort\", \"tennis\" i \"espècie\" són conceptes del cicle vital? Contesta exactament \"sí\" o \"no\"."
  },
  {
    "id": "562",
    "input": "Totes les paraules \"dona\", \"porro\", \"nadó\", \"nena\" i \"senyora\" són persones i gent? Contesta exactament \"sí\" o \"no\"."
  },
  {
    "id": "579",
    "input": "Totes les paraules \"api\", \"pastanaga\", \"carbassa\", \"samarreta\" i \"remolatxa\" són verdures? Contesta exactament \"sí\" o \"no\"."
  },
  {
    "id": "596",
    "input": "Totes les paraules \"granota\", \"gallina\", \"calamar\", \"ocell\" i \"memòria\" són animals? Contesta exactament \"sí\" o \"no\"."
  },
  {
    "id": "890",
    "input": "Totes les paraules \"jaqueta\", \"surf\", \"sostenidor\", \"pantalons\" i \"ulleres\" són peces de roba? Contesta exactament \"sí\" o \"no\"."
  },
  {
    "id": "940",
    "input": "Totes les paraules \"tornado\", \"allau\", \"tsunami\", \"sequera\" i \"cap\" són catàstrofes naturals? Contesta exactament \"sí\" o \"no\"."
  },
  {
    "id": "967",
    "input": "Totes les paraules \"diners\", \"demanda\", \"bitllet\", \"preu\" i \"huracà\" són conceptes d'economia? Contesta exactament \"sí\" o \"no\"."
  },
  {
    "id": "1022",
    "input": "Totes les paraules \"terratrèmol\", \"sequera\", \"tornado\", \"albergínia\" i \"allau\" fan referència a catàstrofes naturals? Contesta exactament \"sí\" o \"no\"."
  },
  {
    "id": "1153",
    "input": "Totes les paraules \"cavaller\", \"diumenge\", \"adolescent\", \"nen\" i \"nadó\" fan referència a persones i gent? Contesta exactament \"sí\" o \"no\"."
  },
  {
    "id": "1319",
    "input": "Totes les paraules \"comèdia\", \"suspens\", \"terror\", \"llit\" i \"fantasia\" fan referència a gèneres de pel·lícules? Contesta exactament \"sí\" o \"no\"."
  },
  {
    "id": "1450",
    "input": "Totes les paraules \"acceleració\", \"agulla\", \"direcció\", \"creixement\" i \"altura\" fan referència a conceptes d'espai i quantitat? Contesta exactament \"sí\" o \"no\"."
  },
  {
    "id": "1501",
    "input": "Totes les paraules \"insecte\", \"elefant\", \"conill\", \"all\" i \"sardina\" fan referència a animals? Contesta exactament \"sí\" o \"no\"."
  },
  {
    "id": "1783",
    "input": "Totes les paraules \"marit\", \"néta\", \"besavi\", \"paraula\" i \"nét\" fan referència a membres de la família? Contesta exactament \"sí\" o \"no\"."
  },
  {
    "id": "1796",
    "input": "Totes les paraules \"dentista\", \"benzinera\", \"bombera\", \"caixera\" i \"esposa\" fan referència a professions? Contesta exactament \"sí\" o \"no\"."
  },
  {
    "id": "1902",
    "input": "Totes les paraules \"cama\", \"estómac\", \"cos\", \"barba\" i \"cérvol\" fan referència a parts del cos humà? Contesta exactament \"sí\" o \"no\"."
  },
  {
    "id": "2005",
    "input": "La llista [\"copisteria\", \"fill\", \"neboda\", \"amor\", \"coneguda\"] conté exclusivament membres de la família? Contesta exactament \"sí\" o \"no\"."
  },
  {
    "id": "2047",
    "input": "La llista [\"cul\", \"cabell\", \"billar\", \"barba\", \"cara\"] conté exclusivament parts del cos humà? Contesta exactament \"sí\" o \"no\"."
  },
  {
    "id": "2048",
    "input": "La llista [\"basquetbol\", \"bitlles\", \"gimnàstica\", \"cavaller\", \"boxa\"] conté exclusivament esports? Contesta exactament \"sí\" o \"no\"."
  },
  {
    "id": "2135",
    "input": "La llista [\"corda\", \"càmera\", \"clau\", \"drama\", \"pom\"] conté exclusivament eines? Contesta exactament \"sí\" o \"no\"."
  },
  {
    "id": "2170",
    "input": "La llista [\"coliflor\", \"col\", \"rave\", \"camp\", \"all\"] conté exclusivament verdures? Contesta exactament \"sí\" o \"no\"."
  },
  {
    "id": "2238",
    "input": "La llista [\"col·lega\", \"reproducció\", \"besàvia\", \"cosí\", \"oncle\"] conté exclusivament membres de la família? Contesta exactament \"sí\" o \"no\"."
  },
  {
    "id": "2605",
    "input": "La llista [\"pom\", \"corda\", \"cordill\", \"llibreria\", \"aparell\"] conté exclusivament eines? Contesta exactament \"sí\" o \"no\"."
  },
  {
    "id": "2650",
    "input": "La llista [\"oceà\", \"muntanya\", \"desert\", \"cadira\", \"camp\"] conté exclusivament conceptes geogràfics? Contesta exactament \"sí\" o \"no\"."
  },
  {
    "id": "2678",
    "input": "La llista [\"exemple\", \"advocada\", \"concepte\", \"projecte\", \"experiència\"] conté exclusivament substantius abstractes? Contesta exactament \"sí\" o \"no\"."
  },
  {
    "id": "2732",
    "input": "La llista [\"escalada\", \"empresari\", \"pintora\", \"director\", \"diputada\"] conté exclusivament professions? Contesta exactament \"sí\" o \"no\"."
  },
  {
    "id": "2827",
    "input": "La llista [\"porc\", \"oncle\", \"col·lega\", \"pare\", \"família\"] conté exclusivament membres de la família? Contesta exactament \"sí\" o \"no\"."
  }
]