[
  {
    "id": "41",
    "input": "Quina paraula rima amb la paraula \"esquena\": \"nena\" o \"aeroport\"?"
  },
  {
    "id": "88",
    "input": "Quina paraula rima amb la paraula \"gas\": \"nas\" o \"lluny\"?"
  },
  {
    "id": "105",
    "input": "Quina paraula rima amb la paraula \"objectiu\": \"ungla\" o \"adjectiu\"?"
  },
  {
    "id": "161",
    "input": "Quina paraula rima amb la paraula \"governadora\": \"calm\" o \"millora\"?"
  },
  {
    "id": "366",
    "input": "Quina paraula rima amb la paraula \"tal\": \"aquí\" o \"cultural\"?"
  },
  {
    "id": "562",
    "input": "Quina paraula rima amb la paraula \"atac\": \"desè\" o \"llimac\"?"
  },
  {
    "id": "579",
    "input": "Quina paraula rima amb la paraula \"venir\": \"distingir\" o \"platja\"?"
  },
  {
    "id": "596",
    "input": "Quina paraula rima amb la paraula \"cambrer\": \"potser\" o \"avió\"?"
  },
  {
    "id": "890",
    "input": "Quina paraula rima amb la paraula \"empresari\": \"necessari\" o \"programa\"?"
  },
  {
    "id": "940",
    "input": "Quina paraula rima amb la paraula \"escola\": \"bestiola\" o \"gos\"?"
  },
  {
    "id": "967",
    "input": "Quina paraula rima amb la paraula \"senyora\": \"governadora\" o \"gent\"?"
  },
  {
    "id": "1022",
    "input": "Quina és una rima de la paraula \"estricte\": \"conflicte\" o \"pau\"?"
  },
  {
    "id": "1153",
    "input": "Quina és una rima de la paraula \"intercanviar\": \"aferrar\" o \"absolut\"?"
  },
  {
    "id": "1319",
    "input": "Quina és una rima de la paraula \"perquè\": \"tema\" o \"cinquè\"?"
  },
  {
    "id": "1450",
    "input": "Quina és una rima de la paraula \"autoritat\": \"faves\" o \"ciutat\"?"
  },
  {
    "id": "1501",
    "input": "Quina és una rima de la paraula \"senyor\": \"lampista\" o \"banyador\"?"
  },
  {
    "id": "1783",
    "input": "Quina és una rima de la paraula \"conjunt\": \"tia\" o \"damunt\"?"
  },
  {
    "id": "1796",
    "input": "Quina és una rima de la paraula \"substantiu\": \"administratiu\" o \"poc\"?"
  },
  {
    "id": "1902",
    "input": "Quina és una rima de la paraula \"suggerir\": \"dimecres\" o \"seguir\"?"
  },
  {
    "id": "2005",
    "input": "De les paraules \"escriure\" i \"clau\", quina rima amb \"suau\"?"
  },
  {
    "id": "2047",
    "input": "De les paraules \"llegir\" i \"cargol\", quina rima amb \"dir\"?"
  },
  {
    "id": "2048",
    "input": "De les paraules \"exactament\" i \"milionèsim\", quina rima amb \"anteriorment\"?"
  },
  {
    "id": "2135",
    "input": "De les paraules \"periodista\" i \"retrocés\", quina rima amb \"dentista\"?"
  },
  {
    "id": "2170",
    "input": "De les paraules \"ocasió\" i \"calamar\", quina rima amb \"rar\"?"
  },
  {
    "id": "2238",
    "input": "De les paraules \"contingut\" i \"camp\", quina rima amb \"gruixut\"?"
  },
  {
    "id": "2605",
    "input": "De les paraules \"bombera\" i \"finalment\", quina rima amb \"deteriorament\"?"
  },
  {
    "id": "2650",
    "input": "De les paraules \"interessat\" i \"oceà\", quina rima amb \"aviat\"?"
  },
  {
    "id": "2678",
    "input": "De les paraules \"amarg\" i \"conegut\", quina rima amb \"llarg\"?"
  },
  {
    "id": "2732",
    "input": "De les paraules \"llavi\" i \"gent\", quina rima amb \"besavi\"?"
  },
  {
    "id": "2827",
    "input": "De les paraules \"esperar\" i \"poc\", quina rima amb \"lloc\"?"
  }
]