[
  {
    "id": "41",
    "input": "Algunha destas palabras \"adulta\", \"exemplo\", \"corda\", \"inundación\" e \"municipio\" son do tipo cores? Responde \"si\" ou \"non\"."
  },
  {
    "id": "88",
    "input": "Algunha destas palabras \"minoría\", \"cordón\", \"nai\", \"cenorias\" e \"encontro\" son do tipo substantivos abstractos? Responde \"si\" ou \"non\"."
  },
  {
    "id": "105",
    "input": "Algunha destas palabras \"vista\", \"formalidade\", \"bolso\", \"cebola\" e \"individuo\" son do tipo profesións? Responde \"si\" ou \"non\"."
  },
  {
    "id": "161",
    "input": "Algunha destas palabras \"esposa\", \"capacidade\", \"dentista\", \"barba\" e \"calidade\" son do tipo economía? Responde \"si\" ou \"non\"."
  },
  {
    "id": "366",
    "input": "Algunha destas palabras \"atención\", \"tráfico\", \"humano\", \"electricista\" e \"equivocación\" son do tipo fogar? Responde \"si\" ou \"non\"."
  },
  {
    "id": "562",
    "input": "Algunha destas palabras \"panadería\", \"escalada\", \"xuíz\", \"corvo\" e \"panel\" son do tipo materiais? Responde \"si\" ou \"non\"."
  },
  {
    "id": "579",
    "input": "Algunha destas palabras \"alcalde\", \"millo\", \"natación\", \"rata\" e \"amigo\" son do tipo substantivos abstractos? Responde \"si\" ou \"non\"."
  },
  {
    "id": "596",
    "input": "Algunha destas palabras \"neto\", \"empresario\", \"aburrimento\", \"araña\" e \"galiña\" son do tipo materiais? Responde \"si\" ou \"non\"."
  },
  {
    "id": "890",
    "input": "Algunha destas palabras \"león\", \"mesa\", \"campaña\", \"mercado\" e \"estrada\" son do tipo catástrofe natural? Responde \"si\" ou \"non\"."
  },
  {
    "id": "940",
    "input": "Algunha destas palabras \"corda\", \"centímetro\", \"total\", \"edificio\" e \"home\" son do tipo días da semana? Responde \"si\" ou \"non\"."
  },
  {
    "id": "967",
    "input": "Algunha destas palabras \"neno\", \"segredo\", \"incendio\", \"congreso\" e \"individuo\" son do tipo deportes? Responde \"si\" ou \"non\"."
  },
  {
    "id": "1022",
    "input": "Dalgunha das palabras \"familia\", \"barco\", \"fantasía\", \"filla\" e \"esgrima\" represéntase substantivos abstractos? Responde \"si\" ou \"non\"."
  },
  {
    "id": "1153",
    "input": "Dalgunha das palabras \"consello\", \"serie\", \"guerra\", \"morte\" e \"batería\" represéntase familia? Responde \"si\" ou \"non\"."
  },
  {
    "id": "1319",
    "input": "Dalgunha das palabras \"coliflor\", \"sal\", \"condición\", \"estanco\" e \"suxeitador\" represéntase fogar? Responde \"si\" ou \"non\"."
  },
  {
    "id": "1450",
    "input": "Dalgunha das palabras \"camiño\", \"remolacha\", \"man\", \"corda\" e \"avó\" represéntase deportes? Responde \"si\" ou \"non\"."
  },
  {
    "id": "1501",
    "input": "Dalgunha das palabras \"cordón\", \"peso\", \"bicho\", \"actriz\" e \"decreto\" represéntase xéneros de películas? Responde \"si\" ou \"non\"."
  },
  {
    "id": "1783",
    "input": "Dalgunha das palabras \"vestido\", \"lombriz\", \"neto\", \"tenis\" e \"trompeta\" represéntase catástrofe natural? Responde \"si\" ou \"non\"."
  },
  {
    "id": "1796",
    "input": "Dalgunha das palabras \"club\", \"caso\", \"asociación\", \"esposo\" e \"ravo\" represéntase vida? Responde \"si\" ou \"non\"."
  },
  {
    "id": "1902",
    "input": "Dalgunha das palabras \"domingo\", \"ovella\", \"pracer\", \"fígado\" e \"autoridade\" represéntase verduras? Responde \"si\" ou \"non\"."
  },
  {
    "id": "2005",
    "input": "Da seguinte lista [\"avó\", \"causa\", \"filla\", \"natureza\", \"tráfico\"] contén algunha días da semana? Responde \"si\" ou \"non\"."
  },
  {
    "id": "2047",
    "input": "Da seguinte lista [\"tigre\", \"vila\", \"azul\", \"esposo\", \"edificio\"] contén algunha medidas? Responde \"si\" ou \"non\"."
  },
  {
    "id": "2048",
    "input": "Da seguinte lista [\"cogombro\", \"branco\", \"corvo\", \"beneficio\", \"grao\"] contén algunha vida? Responde \"si\" ou \"non\"."
  },
  {
    "id": "2135",
    "input": "Da seguinte lista [\"movemento\", \"dormitorio\", \"susto\", \"insecto\", \"peiteador\"] contén algunha xeografía? Responde \"si\" ou \"non\"."
  },
  {
    "id": "2170",
    "input": "Da seguinte lista [\"pomo\", \"piano\", \"repolo\", \"laguna\", \"pel\"] contén algunha días da semana? Responde \"si\" ou \"non\"."
  },
  {
    "id": "2238",
    "input": "Da seguinte lista [\"cogombro\", \"dormitorio\", \"balonmán\", \"rugby\", \"agulla\"] contén algunha substantivos abstractos? Responde \"si\" ou \"non\"."
  },
  {
    "id": "2605",
    "input": "Da seguinte lista [\"cousa\", \"esposo\", \"patinaxe\", \"peso\", \"charcutaría\"] contén algunha corpo humán? Responde \"si\" ou \"non\"."
  },
  {
    "id": "2650",
    "input": "Da seguinte lista [\"terremoto\", \"pantalón\", \"asociación\", \"peso\", \"neta\"] contén algunha transporte? Responde \"si\" ou \"non\"."
  },
  {
    "id": "2678",
    "input": "Da seguinte lista [\"xoiería\", \"botón\", \"prezo\", \"pescozo\", \"nariz\"] contén algunha profesións? Responde \"si\" ou \"non\"."
  },
  {
    "id": "2732",
    "input": "Da seguinte lista [\"escalera\", \"carnizaría\", \"programador\", \"proxecto\", \"terror\"] contén algunha verduras? Responde \"si\" ou \"non\"."
  },
  {
    "id": "2827",
    "input": "Da seguinte lista [\"presente\", \"dedo\", \"salón de peiteado\", \"comedia\", \"natureza\"] contén algunha medidas? Responde \"si\" ou \"non\"."
  }
]