[
  {
    "id": "41",
    "input": "¿Qué palabra rima con la palabra \"caro\": \"raro\" o \"admirar\"?"
  },
  {
    "id": "88",
    "input": "¿Qué palabra rima con la palabra \"probablemente\": \"aburrirse\" o \"inicialmente\"?"
  },
  {
    "id": "105",
    "input": "¿Qué palabra rima con la palabra \"bisabuelo\": \"velo\" o \"seis\"?"
  },
  {
    "id": "161",
    "input": "¿Qué palabra rima con la palabra \"relación\": \"asociación\" o \"partido\"?"
  },
  {
    "id": "366",
    "input": "¿Qué palabra rima con la palabra \"justo\": \"julio\" o \"susto\"?"
  },
  {
    "id": "562",
    "input": "¿Qué palabra rima con la palabra \"evitar\": \"bar\" o \"fracaso\"?"
  },
  {
    "id": "579",
    "input": "¿Qué palabra rima con la palabra \"solitario\": \"necesario\" o \"mundial\"?"
  },
  {
    "id": "596",
    "input": "¿Qué palabra rima con la palabra \"cartero\": \"ligero\" o \"bar\"?"
  },
  {
    "id": "890",
    "input": "¿Qué palabra rima con la palabra \"manual\": \"universal\" o \"espárrago\"?"
  },
  {
    "id": "940",
    "input": "¿Qué palabra rima con la palabra \"medida\": \"avenida\" o \"bueno\"?"
  },
  {
    "id": "967",
    "input": "¿Qué palabra rima con la palabra \"país\": \"gris\" o \"cercano\"?"
  },
  {
    "id": "1022",
    "input": "¿Cuál es una rima de la palabra \"ir\": \"cansado\" o \"oír\"?"
  },
  {
    "id": "1153",
    "input": "¿Cuál es una rima de la palabra \"raro\": \"caro\" o \"río\"?"
  },
  {
    "id": "1319",
    "input": "¿Cuál es una rima de la palabra \"decir\": \"abuela\" o \"salir\"?"
  },
  {
    "id": "1450",
    "input": "¿Cuál es una rima de la palabra \"reír\": \"dormir\" o \"gobernadora\"?"
  },
  {
    "id": "1501",
    "input": "¿Cuál es una rima de la palabra \"cocodrilo\": \"cámara\" o \"hilo\"?"
  },
  {
    "id": "1783",
    "input": "¿Cuál es una rima de la palabra \"espera\": \"diente\" o \"carpintera\"?"
  },
  {
    "id": "1796",
    "input": "¿Cuál es una rima de la palabra \"bar\": \"intercambiar\" o \"contenido\"?"
  },
  {
    "id": "1902",
    "input": "¿Cuál es una rima de la palabra \"actriz\": \"lombriz\" o \"nieto\"?"
  },
  {
    "id": "2005",
    "input": "De las palabras \"angosto\" y \"oreja\", ¿cuál rima con \"agosto\"?"
  },
  {
    "id": "2047",
    "input": "De las palabras \"actualmente\" y \"tío\", ¿cuál rima con \"río\"?"
  },
  {
    "id": "2048",
    "input": "De las palabras \"vuestro\" y \"significado\", ¿cuál rima con \"enfadado\"?"
  },
  {
    "id": "2135",
    "input": "De las palabras \"gato\" y \"ojo\", ¿cuál rima con \"barato\"?"
  },
  {
    "id": "2170",
    "input": "De las palabras \"dejar\" y \"batería\", ¿cuál rima con \"acordar\"?"
  },
  {
    "id": "2238",
    "input": "De las palabras \"consejo\" y \"programador\", ¿cuál rima con \"viejo\"?"
  },
  {
    "id": "2605",
    "input": "De las palabras \"camarero\" y \"amargo\", ¿cuál rima con \"cargo\"?"
  },
  {
    "id": "2650",
    "input": "De las palabras \"tocar\" y \"hotel\", ¿cuál rima con \"cordel\"?"
  },
  {
    "id": "2678",
    "input": "De las palabras \"escuela\" y \"vender\", ¿cuál rima con \"mover\"?"
  },
  {
    "id": "2732",
    "input": "De las palabras \"cuando\" y \"acompañar\", ¿cuál rima con \"blando\"?"
  },
  {
    "id": "2827",
    "input": "De las palabras \"ligero\" y \"librería\", ¿cuál rima con \"tercero\"?"
  }
]