[
  {
    "id": "100",
    "input": "Na frase \"Em março a água do sol e a água estão queimando\", qual palavra vem logo antes da palavra \"do\"?"
  },
  {
    "id": "111",
    "input": "Na frase \"Crescimento da soberania popular revolucionária\", qual palavra vem logo antes da palavra \"da\"?"
  },
  {
    "id": "1159",
    "input": "Na frase \"A voz do anjo corresponde a uma voz de soprano\", que palavra vem imediatamente antes da palavra \"do\"?"
  },
  {
    "id": "1189",
    "input": "Na frase \"Eu não posso ajudar vocês\", que palavra vem imediatamente antes da palavra \"não\"?"
  },
  {
    "id": "1191",
    "input": "Na frase \"Três opiniões em um dia para incentivar as pessoas a se registrarem para votar\", que palavra vem imediatamente antes da palavra \"opiniões\"?"
  },
  {
    "id": "1193",
    "input": "Na frase \"Por San Pedro junho atrás\", que palavra vem imediatamente antes da palavra \"Pedro\"?"
  },
  {
    "id": "1230",
    "input": "Na frase \"As vinícolas cadastradas colaborarão no monitoramento do cumprimento das normas anteriores\", que palavra vem imediatamente antes da palavra \"no\"?"
  },
  {
    "id": "1240",
    "input": "Na frase \"Brigas de marido da mesa à cama\", que palavra vem imediatamente antes da palavra \"da\"?"
  },
  {
    "id": "1290",
    "input": "Na frase \"Posfácio à Segunda Edição Alemã do Livro Primeiro de\", que palavra vem imediatamente antes da palavra \"Edição\"?"
  },
  {
    "id": "1346",
    "input": "Na frase \"Eu recomendo Mouseless Browsing para Firefox e Vimium para Chrome\", que palavra vem imediatamente antes da palavra \"recomendo\"?"
  },
  {
    "id": "137",
    "input": "Na frase \"Sempre faça uma pergunta objetiva\", qual palavra vem logo antes da palavra \"faça\"?"
  },
  {
    "id": "1402",
    "input": "Na frase \"A jornada de trabalho na União Soviética era menor o desemprego quase inexistente\", que palavra vem imediatamente antes da palavra \"inexistente\"?"
  },
  {
    "id": "1424",
    "input": "Na frase \"Cada morcego procura o seu buraco\", que palavra vem imediatamente antes da palavra \"morcego\"?"
  },
  {
    "id": "1546",
    "input": "Na frase \"Traríamos menos do que o que fora insuficiente\", que palavra vem imediatamente antes da palavra \"do\"?"
  },
  {
    "id": "1562",
    "input": "Na frase \"Até uma vida longa tem o seu fim\", que palavra vem imediatamente antes da palavra \"longa\"?"
  },
  {
    "id": "1595",
    "input": "Na frase \"Os segredos das redes sociais para viciar e manipular opiniões\", que palavra vem imediatamente antes da palavra \"das\"?"
  },
  {
    "id": "1596",
    "input": "Na frase \"Esses são os nomes ingleses que pertencem ao meio do show\", que palavra vem imediatamente antes da palavra \"do\"?"
  },
  {
    "id": "1597",
    "input": "Na frase \"Chegámos a Cascais desembarquei e apanhei um autocarro até à praia de Carcavelos\", que palavra vem imediatamente antes da palavra \"um\"?"
  },
  {
    "id": "1677",
    "input": "Na frase \"Realize o estudo da identidade corporativa aplicando técnicas de análise\", que palavra vem imediatamente antes da palavra \"corporativa\"?"
  },
  {
    "id": "170",
    "input": "Na frase \"Não estrague o vinho com água não ame com um casamento\", qual palavra vem logo antes da palavra \"estrague\"?"
  },
  {
    "id": "175",
    "input": "Na frase \"O objetivo era minar a Índia\", qual palavra vem logo antes da palavra \"a\"?"
  },
  {
    "id": "1768",
    "input": "Na frase \"Procurarei a tinta e os pincéis\", que palavra vem imediatamente antes da palavra \"pincéis\"?"
  },
  {
    "id": "1786",
    "input": "Na frase \"O homem que está lidando com amigos ele nunca faltará fadiga\", que palavra vem imediatamente antes da palavra \"que\"?"
  },
  {
    "id": "1910",
    "input": "Na frase \"Sinto que estou prestes a ter um ataque cardíaco\", que palavra vem imediatamente antes da palavra \"cardíaco\"?"
  },
  {
    "id": "192",
    "input": "Na frase \"Se não o fizer o direito do licitante vencedor receberá o auxílio\", qual palavra vem logo antes da palavra \"direito\"?"
  },
  {
    "id": "1987",
    "input": "Na frase \"Eles combinam a centralização e soberania do povo\", que palavra vem imediatamente antes da palavra \"do\"?"
  },
  {
    "id": "1995",
    "input": "Na frase \"O que é possível diante de um caos tão insignificante?\", que palavra vem imediatamente antes da palavra \"insignificante?\"?"
  },
  {
    "id": "2085",
    "input": "Que palavra está logo antes da palavra \"a\" na frase \"Todavia a adoção de políticas descentralizadoras é uma das consequências do sistema\"?"
  },
  {
    "id": "2116",
    "input": "Que palavra está logo antes da palavra \"é\" na frase \"O fascismo é o botão de emergência dos capitalistas\"?"
  },
  {
    "id": "2137",
    "input": "Que palavra está logo antes da palavra \"faça\" na frase \"Sempre faça uma pergunta objetiva\"?"
  },
  {
    "id": "2148",
    "input": "Que palavra está logo antes da palavra \"forte\" na frase \"Raios dessa aurora forte são como beijos de mãe\"?"
  },
  {
    "id": "221",
    "input": "Na frase \"A pasta pode limpar o latão mais sujo\", qual palavra vem logo antes da palavra \"sujo\"?"
  },
  {
    "id": "246",
    "input": "Na frase \"Aqui vende roupinhas para capivaras?\", qual palavra vem logo antes da palavra \"vende\"?"
  },
  {
    "id": "2698",
    "input": "Que palavra está logo antes da palavra \"de\" na frase \"Treinamento de voz e técnicas robóticas\"?"
  },
  {
    "id": "2914",
    "input": "Que palavra está logo antes da palavra \"aceito\" na frase \"Eu não aceito este diagnóstico\"?"
  },
  {
    "id": "376",
    "input": "Na frase \"Ellie ganhou o primeiro prêmio na competição de ortografia\", qual palavra vem logo antes da palavra \"prêmio\"?"
  },
  {
    "id": "422",
    "input": "Na frase \"Beleza puxa mais de dez volumes\", qual palavra vem logo antes da palavra \"puxa\"?"
  },
  {
    "id": "425",
    "input": "Na frase \"O templo fica no alto da colina de onde é possível observar o horizonte\", qual palavra vem logo antes da palavra \"de\"?"
  },
  {
    "id": "477",
    "input": "Na frase \"Sua história era tão absurda que ninguém acreditava\", qual palavra vem logo antes da palavra \"acreditava\"?"
  },
  {
    "id": "481",
    "input": "Na frase \"O que mostram os sinais de uma cadeia alimentar?\", qual palavra vem logo antes da palavra \"de\"?"
  },
  {
    "id": "507",
    "input": "Na frase \"Getúlio Vargas foi um presidente aclamado pela história\", qual palavra vem logo antes da palavra \"Vargas\"?"
  },
  {
    "id": "554",
    "input": "Na frase \"Nós viemos do baronato de Rialb\", qual palavra vem logo antes da palavra \"viemos\"?"
  },
  {
    "id": "562",
    "input": "Na frase \"Até uma vida longa tem o seu fim\", qual palavra vem logo antes da palavra \"longa\"?"
  },
  {
    "id": "57",
    "input": "Na frase \"Nossa hoje foi um dia bem merda\", qual palavra vem logo antes da palavra \"hoje\"?"
  },
  {
    "id": "633",
    "input": "Na frase \"Ela agora gosta de sua preocupação no começo\", qual palavra vem logo antes da palavra \"agora\"?"
  },
  {
    "id": "639",
    "input": "Na frase \"Ele já sabia seus pensamentos o trabalho era coisa do diabo\", qual palavra vem logo antes da palavra \"seus\"?"
  },
  {
    "id": "71",
    "input": "Na frase \"O mais do tempo é gasto em hortar jardinar e ler\", qual palavra vem logo antes da palavra \"jardinar\"?"
  },
  {
    "id": "715",
    "input": "Na frase \"Quando os cães pegam algo que sentem\", qual palavra vem logo antes da palavra \"os\"?"
  },
  {
    "id": "756",
    "input": "Na frase \"Desta vez o elétrico vinha cheio até às tampas\", qual palavra vem logo antes da palavra \"cheio\"?"
  },
  {
    "id": "783",
    "input": "Na frase \"Fazer cessar ou extinguir aquilo que causara o sofrimento\", qual palavra vem logo antes da palavra \"cessar\"?"
  },
  {
    "id": "792",
    "input": "Na frase \"Foi um erro eu ter confiado nele\", qual palavra vem logo antes da palavra \"ter\"?"
  },
  {
    "id": "814",
    "input": "Na frase \"Os olhos são o primeiro lugar do amor\", qual palavra vem logo antes da palavra \"são\"?"
  },
  {
    "id": "852",
    "input": "Na frase \"Cumprindo uma obrigação no terreiro\", qual palavra vem logo antes da palavra \"uma\"?"
  },
  {
    "id": "875",
    "input": "Na frase \"Ela realmente precisava dormir na noite passada então quando é melhor pegar de manhã?\", qual palavra vem logo antes da palavra \"realmente\"?"
  },
  {
    "id": "878",
    "input": "Na frase \"Traríamos menos do que o que fora insuficiente\", qual palavra vem logo antes da palavra \"fora\"?"
  },
  {
    "id": "890",
    "input": "Na frase \"A lavagem de dinheiro foi feita com sucesso\", qual palavra vem logo antes da palavra \"de\"?"
  },
  {
    "id": "97",
    "input": "Na frase \"União Soviética e a China\", qual palavra vem logo antes da palavra \"China\"?"
  },
  {
    "id": "980",
    "input": "Na frase \"Eu acho que vou me juntar ao grupo neste final de semana\", qual palavra vem logo antes da palavra \"de\"?"
  },
  {
    "id": "984",
    "input": "Na frase \"Use um casaco e morra quente\", qual palavra vem logo antes da palavra \"quente\"?"
  },
  {
    "id": "987",
    "input": "Na frase \"Eles combinam a centralização e soberania do povo\", qual palavra vem logo antes da palavra \"do\"?"
  }
]